CHANGES
COPYING.LGPLv3
LICENSE
MANIFEST.in
README
ez_setup.py
requirements.txt
setup.py
django_player.egg-info/PKG-INFO
django_player.egg-info/SOURCES.txt
django_player.egg-info/dependency_links.txt
django_player.egg-info/entry_points.txt
django_player.egg-info/requires.txt
django_player.egg-info/top_level.txt
example_project/__init__.py
example_project/manage.py
example_project/settings.py
example_project/urls.py
example_project/items/__init__.py
example_project/items/blocks.py
example_project/items/models.py
example_project/items/tests.py
example_project/items/views.py
example_project/news/__init__.py
example_project/news/admin.py
example_project/news/blocks.py
example_project/news/models.py
example_project/news/tests.py
example_project/news/urls.py
example_project/news/views.py
example_project/website/__init__.py
example_project/website/blocks.py
example_project/website/models.py
example_project/website/tests.py
example_project/website/views.py
player/__init__.py
player/context_processors.py
player/settings.py
player/base/__init__.py
player/base/dbfields.py
player/base/fields.py
player/base/forms.py
player/base/params.py
player/base/views.py
player/base/widgets.py
player/base/management/__init__.py
player/base/management/base.py
player/base/static/base/css/admin.css
player/base/static/base/css/base.css
player/base/static/base/css/reset.css
player/base/static/base/css/toolbar.css
player/base/static/base/img/close.gif
player/base/static/base/img/slide_next.gif
player/base/static/base/img/slide_previous.gif
player/base/static/base/img/white.jpg
player/base/static/base/js/jquery-ui.min.js
player/base/static/base/js/jquery.autopaginate_link_tabs.js
player/base/static/base/js/jquery.csrf.js
player/base/static/base/js/jquery.generic-delete.js
player/base/static/base/js/jquery.jeditable.mini.js
player/base/static/base/js/jquery.min.js
player/base/static/base/js/jquery.simulate.js
player/base/static/base/js/less.js
player/base/static/inlinetrans/css/inlinetrans.css
player/base/static/inlinetrans/img/ajax-loader-transparent.gif
player/base/static/inlinetrans/js/jquery.inlinetrans.js
player/base/templates/base.html
player/base/templates/inc.breadcrumbs.html
